dealstat/__init__.py
dealstat/address.py
dealstat/boto.py
dealstat/dealstat.py
dealstat/ml.py
dealstat-0.1.5.dist-info/AUTHORS.rst
dealstat-0.1.5.dist-info/LICENSE
dealstat-0.1.5.dist-info/METADATA
dealstat-0.1.5.dist-info/WHEEL
dealstat-0.1.5.dist-info/top_level.txt
dealstat-0.1.5.dist-info/RECORD
