Metadata-Version: 2.1
Name: dealstat
Version: 0.1.5
Summary: DealStat Utilities
Home-page: https://github.com/DealStat/DealStat-Utilities
Author: DealStat REI
Author-email: developer@dealstatrei.com
License: MIT license
Keywords: dealstat
Platform: UNKNOWN
Classifier: Development Status :: 2 - Pre-Alpha
Classifier: Intended Audience :: Developers
Classifier: License :: OSI Approved :: MIT License
Classifier: Natural Language :: English
Classifier: Programming Language :: Python :: 3
Classifier: Programming Language :: Python :: 3.4
Classifier: Programming Language :: Python :: 3.5
Classifier: Programming Language :: Python :: 3.6
Classifier: Programming Language :: Python :: 3.7
Requires-Dist: boto3 (>=1.9.77)
Requires-Dist: regex (>=2018.11.22)
Requires-Dist: numpy (>=1.16.0)
Requires-Dist: usaddress (==0.5.10)
